{
  "time": 20.617066860198975,
  "configuration": {
    "mutation_type": "wouter",
    "generation_type": "asymmetric",
    "distribution": "lognormal",
    "city_size": 20,
    "range": 3.0
  },
  "results": {
    "initial_matrix": [],
    "hard_instances": {
      "iteration_0": {
        "iterations": 60,
        "hardest": 60,
        "optimal_tour": [
          [
            8,
            4
          ],
          [
            11,
            0
          ],
          [
            2,
            15
          ],
          [
            1,
            10
          ],
          [
            10,
            7
          ],
          [
            17,
            6
          ],
          [
            7,
            13
          ],
          [
            4,
            14
          ],
          [
            0,
            5
          ],
          [
            5,
            2
          ],
          [
            3,
            18
          ],
          [
            9,
            12
          ],
          [
            16,
            8
          ],
          [
            14,
            3
          ],
          [
            12,
            19
          ],
          [
            13,
            16
          ],
          [
            6,
            9
          ],
          [
            15,
            17
          ],
          [
            18,
            11
          ],
          [
            19,
            1
          ]
        ],
        "optimal_cost": 6374.0,
        "matrix": [
          [
            Infinity,
            1006917.0,
            301611.0,
            1728178.0,
            100436.0,
            457.0,
            172140.0,
            9059.0,
            17347.0,
            11023.0,
            2041.0,
            45862.0,
            198184.0,
            914.0,
            136752.0,
            177257.0,
            2290232.0,
            24368.0,
            2701.0,
            106369.0
          ],
          [
            89931.0,
            Infinity,
            210968.0,
            83865.0,
            34817.0,
            112503.0,
            165832.0,
            38300549.0,
            41248.0,
            19487473.0,
            1652.0,
            32.0,
            24218.0,
            199929.0,
            5116.0,
            1650.0,
            6159.0,
            19562.0,
            7906.0,
            151500.0
          ],
          [
            168997.0,
            13233.0,
            Infinity,
            2617.0,
            46967.0,
            406.0,
            686086.0,
            36340.0,
            24568.0,
            11717.0,
            19315.0,
            1562.0,
            231854.0,
            8451.0,
            23852.0,
            101.0,
            6601.0,
            4541.0,
            2214.0,
            184629.0
          ],
          [
            54660.0,
            52339.0,
            252.0,
            Infinity,
            29795.0,
            944975.0,
            346.0,
            199.0,
            8150.0,
            35503.0,
            9500.0,
            189587.0,
            18196.0,
            3289.0,
            3808.0,
            31631.0,
            621726.0,
            258162.0,
            21.0,
            142623.0
          ],
          [
            6.0,
            125708.0,
            774.0,
            3415.0,
            Infinity,
            9376.0,
            47040.0,
            1997.0,
            14924.0,
            12103.0,
            2470.0,
            6416241.0,
            5058.0,
            9726970.0,
            562.0,
            51.0,
            33022.0,
            490636.0,
            121270.0,
            137009.0
          ],
          [
            153397.0,
            30939.0,
            151.0,
            8.0,
            172922.0,
            Infinity,
            16578.0,
            182598.0,
            48811.0,
            7966.0,
            65901.0,
            193167.0,
            2000315.0,
            41740.0,
            340.0,
            48435.0,
            17280.0,
            2975.0,
            4768.0,
            468357.0
          ],
          [
            7284.0,
            174391.0,
            8706.0,
            6145.0,
            47034.0,
            62148.0,
            Infinity,
            454982.0,
            79369.0,
            62.0,
            3807.0,
            32968.0,
            19047.0,
            1480.0,
            4994.0,
            2159.0,
            13433.0,
            665133.0,
            35301.0,
            11700.0
          ],
          [
            5371305.0,
            7343.0,
            7846377.0,
            2378939.0,
            86140.0,
            31205994.0,
            9.0,
            Infinity,
            1041.0,
            587.0,
            7158.0,
            6474.0,
            45309090.0,
            422.0,
            227594.0,
            458.0,
            3163485.0,
            7373.0,
            63063.0,
            642.0
          ],
          [
            421.0,
            187.0,
            2944846.0,
            1180.0,
            1.0,
            35941.0,
            226928.0,
            30004.0,
            Infinity,
            44279.0,
            4771.0,
            15292.0,
            65010.0,
            7879.0,
            891621.0,
            9562406.0,
            533032.0,
            2525.0,
            724.0,
            240052.0
          ],
          [
            102.0,
            41762.0,
            230991.0,
            47942.0,
            22757.0,
            9994.0,
            2947.0,
            6421.0,
            1463250.0,
            Infinity,
            1874005.0,
            26824.0,
            54.0,
            204882.0,
            161.0,
            98560.0,
            4431.0,
            73510.0,
            327.0,
            331265682.0
          ],
          [
            1986121.0,
            108.0,
            20203997.0,
            82663.0,
            1731238.0,
            6215.0,
            166518.0,
            293.0,
            4375010.0,
            5387544.0,
            Infinity,
            26672.0,
            11173.0,
            4186.0,
            110868.0,
            49682.0,
            329.0,
            1547233.0,
            20158.0,
            1231.0
          ],
          [
            171.0,
            35660.0,
            193300.0,
            1799.0,
            389.0,
            5458.0,
            1526711.0,
            293250.0,
            39722.0,
            29354.0,
            14042.0,
            Infinity,
            1726.0,
            297867.0,
            48342.0,
            343.0,
            996.0,
            86425.0,
            97198.0,
            311816.0
          ],
          [
            3164.0,
            543.0,
            78.0,
            40225.0,
            38.0,
            129968.0,
            36281.0,
            5416229.0,
            5032.0,
            172044.0,
            4263.0,
            94280.0,
            Infinity,
            1666.0,
            323020.0,
            121317.0,
            5051.0,
            7606.0,
            498046.0,
            49.0
          ],
          [
            500.0,
            1582097.0,
            406.0,
            16220.0,
            1293.0,
            14333906.0,
            611.0,
            68782.0,
            11917.0,
            18747.0,
            121995.0,
            130599.0,
            3071.0,
            Infinity,
            494131.0,
            7681.0,
            32.0,
            42200.0,
            16521.0,
            62116.0
          ],
          [
            1112709.0,
            283169.0,
            20143.0,
            671.0,
            29365.0,
            104455.0,
            11939.0,
            421081.0,
            739558.0,
            402026561.0,
            4637375.0,
            109406.0,
            81651.0,
            108826.0,
            Infinity,
            723428.0,
            398686.0,
            29546.0,
            126650.0,
            1212.0
          ],
          [
            577.0,
            1916.0,
            3106.0,
            60980.0,
            65937.0,
            216.0,
            45242.0,
            248.0,
            30306.0,
            6616.0,
            1691.0,
            90736.0,
            30202.0,
            190010.0,
            620549.0,
            Infinity,
            15078.0,
            336.0,
            6715.0,
            279078.0
          ],
          [
            7779.0,
            396.0,
            60694.0,
            55196.0,
            951.0,
            60089.0,
            2111.0,
            844110.0,
            762.0,
            8134.0,
            933199.0,
            1206.0,
            245.0,
            46238.0,
            2903862.0,
            20132.0,
            Infinity,
            306816.0,
            66564.0,
            154131.0
          ],
          [
            43711.0,
            3642.0,
            7088.0,
            3584.0,
            685.0,
            489982.0,
            85.0,
            420.0,
            13450.0,
            64088.0,
            35139.0,
            5243107.0,
            3795.0,
            11006.0,
            4443.0,
            21.0,
            2872.0,
            Infinity,
            4542.0,
            36502887.0
          ],
          [
            3314.0,
            62.0,
            2668.0,
            1639.0,
            1178296.0,
            1207946.0,
            51970.0,
            2385088.0,
            976.0,
            18753.0,
            375371.0,
            292.0,
            400812.0,
            6516.0,
            2318.0,
            10178.0,
            322.0,
            4092.0,
            Infinity,
            86421.0
          ],
          [
            3101.0,
            200.0,
            18599.0,
            1187.0,
            253.0,
            9579.0,
            44.0,
            1357053.0,
            12116989.0,
            241.0,
            5667.0,
            238.0,
            442.0,
            13885.0,
            8049.0,
            127.0,
            603.0,
            15446.0,
            1837511.0,
            Infinity
          ]
        ],
        "is_hardest": true
      },
      "iteration_2": {
        "iterations": 93,
        "hardest": 93,
        "optimal_tour": [
          [
            1,
            5
          ],
          [
            12,
            19
          ],
          [
            15,
            0
          ],
          [
            8,
            6
          ],
          [
            18,
            7
          ],
          [
            11,
            8
          ],
          [
            2,
            16
          ],
          [
            9,
            18
          ],
          [
            10,
            9
          ],
          [
            7,
            11
          ],
          [
            6,
            13
          ],
          [
            19,
            2
          ],
          [
            14,
            15
          ],
          [
            17,
            4
          ],
          [
            3,
            12
          ],
          [
            5,
            10
          ],
          [
            13,
            3
          ],
          [
            16,
            17
          ],
          [
            0,
            1
          ],
          [
            4,
            14
          ]
        ],
        "optimal_cost": 8627.0,
        "matrix": [
          [
            Infinity,
            31.0,
            16590.0,
            2724.0,
            18578.0,
            2398.0,
            175.0,
            28066.0,
            928951.0,
            26474.0,
            7585.0,
            1090.0,
            17342.0,
            9012065.0,
            145584.0,
            98998.0,
            18318.0,
            181111.0,
            15027.0,
            14892.0
          ],
          [
            18867.0,
            Infinity,
            60192.0,
            188040.0,
            10339.0,
            16.0,
            95.0,
            97452.0,
            284023.0,
            9190.0,
            47383.0,
            169709.0,
            147149.0,
            2203.0,
            214.0,
            1002.0,
            2384232.0,
            2407.0,
            9758637.0,
            135207.0
          ],
          [
            3337.0,
            303.0,
            Infinity,
            2502.0,
            72331.0,
            187.0,
            107837.0,
            720.0,
            950384.0,
            78308.0,
            56252.0,
            290145.0,
            14103.0,
            1793.0,
            400837.0,
            556477.0,
            249.0,
            20808.0,
            397138.0,
            43421.0
          ],
          [
            2361.0,
            160739.0,
            157.0,
            Infinity,
            696.0,
            163.0,
            170005.0,
            28991.0,
            3020.0,
            51526.0,
            10766.0,
            7161285.0,
            433.0,
            243.0,
            68667.0,
            18499.0,
            9831039.0,
            3337.0,
            15287.0,
            500002.0
          ],
          [
            8906.0,
            131.0,
            58840.0,
            4933.0,
            Infinity,
            366569.0,
            37944.0,
            4848.0,
            6382.0,
            476916.0,
            13979.0,
            29655.0,
            24641.0,
            35291.0,
            161.0,
            615.0,
            531523.0,
            17850.0,
            135444.0,
            12739.0
          ],
          [
            29012.0,
            142.0,
            774.0,
            527.0,
            11285.0,
            Infinity,
            9682906.0,
            2630821.0,
            16324.0,
            6046.0,
            879.0,
            396.0,
            59.0,
            107230.0,
            10029.0,
            1669351.0,
            88393.0,
            4352.0,
            797947.0,
            117867.0
          ],
          [
            122534.0,
            285.0,
            38236.0,
            37390.0,
            850.0,
            15311.0,
            Infinity,
            1155496.0,
            260.0,
            371407.0,
            1603.0,
            136819.0,
            98572.0,
            295.0,
            59026.0,
            8097.0,
            926.0,
            196230.0,
            29.0,
            9387.0
          ],
          [
            556.0,
            127268.0,
            24915.0,
            1114145.0,
            7749.0,
            304983.0,
            1687.0,
            Infinity,
            37772.0,
            107411.0,
            22929.0,
            27.0,
            19437.0,
            34792.0,
            710324.0,
            100276.0,
            86992.0,
            255485.0,
            869.0,
            2891.0
          ],
          [
            706.0,
            26867.0,
            2925818.0,
            2262159.0,
            21148.0,
            57109.0,
            431.0,
            283957.0,
            Infinity,
            12437637.0,
            10112.0,
            85.0,
            47150.0,
            51519.0,
            5171.0,
            567874.0,
            1224.0,
            11122.0,
            19435.0,
            77220.0
          ],
          [
            15708.0,
            795.0,
            133198.0,
            1527.0,
            12131.0,
            389868.0,
            966.0,
            2998574.0,
            39364.0,
            Infinity,
            16590.0,
            1944.0,
            86841.0,
            1892.0,
            811366.0,
            69201.0,
            98553.0,
            4183916.0,
            1164.0,
            1184.0
          ],
          [
            16167.0,
            141.0,
            3671.0,
            3704.0,
            287946.0,
            7006.0,
            6480.0,
            6056.0,
            351971.0,
            273.0,
            Infinity,
            14741.0,
            2195.0,
            19002.0,
            504006.0,
            7011431.0,
            299.0,
            9643.0,
            304.0,
            9741.0
          ],
          [
            7665.0,
            5528.0,
            1455388.0,
            457356.0,
            6935.0,
            880.0,
            1266.0,
            2378.0,
            46.0,
            565.0,
            184176.0,
            Infinity,
            779262.0,
            29841.0,
            661.0,
            16421.0,
            39090.0,
            37027.0,
            30796.0,
            131623.0
          ],
          [
            39131.0,
            7433.0,
            2533.0,
            4394.0,
            8740.0,
            279.0,
            324.0,
            1634.0,
            678840.0,
            1881234.0,
            3011669.0,
            32683.0,
            Infinity,
            110162.0,
            1566.0,
            12876.0,
            353095.0,
            76890.0,
            217120.0,
            253.0
          ],
          [
            67956.0,
            13938.0,
            265749.0,
            673.0,
            107983.0,
            50679.0,
            40687.0,
            22528.0,
            13661095.0,
            13176.0,
            53927.0,
            3209.0,
            1314142.0,
            Infinity,
            69180.0,
            54411.0,
            1570906.0,
            12.0,
            1261.0,
            951503.0
          ],
          [
            56103.0,
            12355.0,
            469.0,
            14306.0,
            87003.0,
            3803.0,
            412.0,
            6840.0,
            1163208.0,
            26008.0,
            2568.0,
            280985.0,
            44338.0,
            670.0,
            Infinity,
            187.0,
            491794.0,
            3155637.0,
            194243.0,
            258939.0
          ],
          [
            255.0,
            368181.0,
            2344.0,
            19369.0,
            50526.0,
            115.0,
            5413.0,
            165.0,
            69277.0,
            47832.0,
            5676.0,
            48053.0,
            114938.0,
            1263282.0,
            6389.0,
            Infinity,
            441283.0,
            15508.0,
            300215.0,
            220.0
          ],
          [
            29294.0,
            19850.0,
            104413.0,
            102112.0,
            1034220.0,
            5978.0,
            67656.0,
            9198401.0,
            1437532.0,
            586481.0,
            9021.0,
            1511946.0,
            534867.0,
            2757.0,
            100343.0,
            152425.0,
            Infinity,
            1539.0,
            1978128.0,
            28007.0
          ],
          [
            32410.0,
            6715.0,
            4204.0,
            91614.0,
            221.0,
            70.0,
            2269.0,
            7349.0,
            966.0,
            125201.0,
            495228.0,
            2024.0,
            7406.0,
            219316.0,
            25525.0,
            7185.0,
            276135.0,
            Infinity,
            35460.0,
            10524.0
          ],
          [
            32186.0,
            5108.0,
            47699.0,
            23426.0,
            3034.0,
            587339.0,
            100900.0,
            467.0,
            183.0,
            4759217.0,
            100375.0,
            17628.0,
            24225.0,
            72775.0,
            4454773.0,
            28002.0,
            942008.0,
            1114640.0,
            Infinity,
            1755.0
          ],
          [
            19157.0,
            31967.0,
            1027.0,
            222.0,
            2313560.0,
            3577592.0,
            517712.0,
            560969.0,
            99145.0,
            878426.0,
            104841.0,
            10947.0,
            4192169.0,
            1454.0,
            232325.0,
            4687954.0,
            120019.0,
            33301.0,
            154226.0,
            Infinity
          ]
        ],
        "is_hardest": true
      },
      "iteration_12": {
        "iterations": 94,
        "hardest": 94,
        "optimal_tour": [
          [
            3,
            1
          ],
          [
            16,
            2
          ],
          [
            19,
            17
          ],
          [
            7,
            13
          ],
          [
            9,
            7
          ],
          [
            5,
            9
          ],
          [
            14,
            16
          ],
          [
            13,
            12
          ],
          [
            18,
            8
          ],
          [
            11,
            15
          ],
          [
            15,
            10
          ],
          [
            2,
            0
          ],
          [
            1,
            5
          ],
          [
            12,
            14
          ],
          [
            6,
            3
          ],
          [
            17,
            11
          ],
          [
            4,
            6
          ],
          [
            8,
            4
          ],
          [
            0,
            19
          ],
          [
            10,
            18
          ]
        ],
        "optimal_cost": 8990.0,
        "matrix": [
          [
            Infinity,
            58.0,
            198544.0,
            137.0,
            26039.0,
            3048516.0,
            4211.0,
            44102.0,
            282777.0,
            2080.0,
            18680.0,
            484.0,
            1281932.0,
            180236.0,
            3758.0,
            61788.0,
            2331579.0,
            40050.0,
            250.0,
            930.0
          ],
          [
            556.0,
            Infinity,
            997.0,
            5363.0,
            86877.0,
            600.0,
            40825.0,
            1295.0,
            10749.0,
            2465.0,
            2096802.0,
            683538.0,
            297986.0,
            9393.0,
            94715.0,
            963.0,
            90192.0,
            4762.0,
            16512.0,
            23023.0
          ],
          [
            337.0,
            64682.0,
            Infinity,
            7808.0,
            8218.0,
            565.0,
            3423032.0,
            1620.0,
            523172.0,
            4977446.0,
            71.0,
            45474.0,
            3175.0,
            13712.0,
            1208.0,
            285469.0,
            73.0,
            2112225.0,
            16315.0,
            404.0
          ],
          [
            1180.0,
            301.0,
            242526.0,
            Infinity,
            8369976.0,
            5465.0,
            7041.0,
            5133040.0,
            3017.0,
            26815.0,
            2367.0,
            273102.0,
            85010.0,
            68971.0,
            48317.0,
            146027.0,
            6199.0,
            643.0,
            17164.0,
            1605.0
          ],
          [
            27054.0,
            28828.0,
            563.0,
            819.0,
            Infinity,
            42845.0,
            93.0,
            105305.0,
            45780.0,
            3376.0,
            714.0,
            465.0,
            101.0,
            343.0,
            25293.0,
            171821.0,
            2474.0,
            260.0,
            1316.0,
            62.0
          ],
          [
            97244.0,
            1245.0,
            468.0,
            24422.0,
            1535830.0,
            Infinity,
            3254.0,
            33.0,
            17343.0,
            16.0,
            1023036.0,
            29072.0,
            71673.0,
            11419.0,
            10858.0,
            125058.0,
            204391.0,
            17085.0,
            283.0,
            11323.0
          ],
          [
            22069.0,
            2518.0,
            3808.0,
            1495.0,
            17542.0,
            17201.0,
            Infinity,
            92550.0,
            6437.0,
            54416272.0,
            98825.0,
            1344.0,
            86325.0,
            118759.0,
            55341.0,
            5119.0,
            61862.0,
            57347.0,
            110466.0,
            6685.0
          ],
          [
            20834.0,
            1183950.0,
            81762.0,
            10033.0,
            307031.0,
            1910.0,
            37311.0,
            Infinity,
            124658.0,
            6601.0,
            8198.0,
            132002.0,
            8839.0,
            209.0,
            7512.0,
            81214.0,
            43805.0,
            26973.0,
            20.0,
            17613.0
          ],
          [
            2923558.0,
            47105.0,
            61198.0,
            353.0,
            1660.0,
            795605.0,
            2089673.0,
            57117.0,
            Infinity,
            75153.0,
            60202.0,
            5576.0,
            18929.0,
            244.0,
            113918.0,
            13113.0,
            1117831.0,
            62800.0,
            1467.0,
            186697.0
          ],
          [
            181362.0,
            25174.0,
            194.0,
            1528.0,
            464097.0,
            338796.0,
            64766.0,
            129.0,
            2265228.0,
            Infinity,
            9046.0,
            105.0,
            4297.0,
            445.0,
            317.0,
            16215.0,
            15672.0,
            1219.0,
            339534.0,
            19064.0
          ],
          [
            192234.0,
            2250.0,
            284.0,
            15377.0,
            7122.0,
            50354.0,
            4165.0,
            53239.0,
            33183.0,
            9386.0,
            Infinity,
            181.0,
            16508.0,
            3996023.0,
            75.0,
            974.0,
            40478.0,
            1648097.0,
            172.0,
            683.0
          ],
          [
            182041.0,
            3901.0,
            70.0,
            58613.0,
            248886.0,
            115294.0,
            31180.0,
            1049.0,
            461.0,
            68413.0,
            13641.0,
            Infinity,
            16641.0,
            43870.0,
            300137.0,
            641.0,
            4437.0,
            10641.0,
            707905.0,
            4200789.0
          ],
          [
            3305.0,
            177090.0,
            30440.0,
            656.0,
            5003.0,
            2939.0,
            9122.0,
            100963.0,
            295191.0,
            6101.0,
            25676.0,
            481122.0,
            Infinity,
            14895.0,
            440.0,
            44129.0,
            903.0,
            41075.0,
            8262.0,
            30821.0
          ],
          [
            2161.0,
            1744391.0,
            30092.0,
            1199508.0,
            51704.0,
            48339.0,
            73763.0,
            9204.0,
            99938.0,
            6152.0,
            6998.0,
            149939.0,
            561.0,
            Infinity,
            139163.0,
            6935.0,
            413.0,
            1981923.0,
            282593.0,
            1070665.0
          ],
          [
            35441.0,
            291453.0,
            107666.0,
            55149.0,
            136587.0,
            139869.0,
            18850.0,
            2433.0,
            61497.0,
            406.0,
            219413.0,
            324713.0,
            55663.0,
            1886.0,
            Infinity,
            3192592.0,
            10.0,
            230931.0,
            247674.0,
            108201.0
          ],
          [
            82102.0,
            333.0,
            230.0,
            4511.0,
            69481.0,
            4881.0,
            21802.0,
            3282.0,
            7157763.0,
            8856.0,
            501.0,
            86226.0,
            2532.0,
            2511.0,
            249907.0,
            Infinity,
            17432.0,
            10653.0,
            306196.0,
            67352.0
          ],
          [
            4877.0,
            267723.0,
            304.0,
            27624.0,
            32226.0,
            206507.0,
            1198.0,
            8729451.0,
            4508.0,
            1731811.0,
            3044110.0,
            39451.0,
            876.0,
            89907.0,
            135071.0,
            23330.0,
            Infinity,
            196.0,
            282978.0,
            372398.0
          ],
          [
            9051581.0,
            1924.0,
            1246131.0,
            38830.0,
            17755.0,
            1413.0,
            3434.0,
            79046.0,
            91308.0,
            23925.0,
            66073548.0,
            67.0,
            6617.0,
            63414762.0,
            3292136.0,
            287665.0,
            582.0,
            Infinity,
            16826.0,
            923.0
          ],
          [
            11838.0,
            333.0,
            1993141.0,
            10074.0,
            109477.0,
            185213.0,
            10015.0,
            5835.0,
            318.0,
            28963.0,
            8067.0,
            26462.0,
            155.0,
            2743.0,
            99064.0,
            1565.0,
            474.0,
            346404.0,
            Infinity,
            4183.0
          ],
          [
            9433.0,
            3443.0,
            2061.0,
            71431.0,
            1918393.0,
            3127.0,
            1601.0,
            668.0,
            31027.0,
            327402.0,
            6458927.0,
            52795.0,
            17576.0,
            12159.0,
            3768.0,
            1258.0,
            529.0,
            206.0,
            11368.0,
            Infinity
          ]
        ],
        "is_hardest": true
      },
      "iteration_18": {
        "iterations": 129,
        "hardest": 129,
        "optimal_tour": [
          [
            14,
            6
          ],
          [
            3,
            17
          ],
          [
            1,
            9
          ],
          [
            5,
            0
          ],
          [
            4,
            19
          ],
          [
            8,
            11
          ],
          [
            0,
            8
          ],
          [
            9,
            12
          ],
          [
            17,
            2
          ],
          [
            15,
            10
          ],
          [
            2,
            4
          ],
          [
            11,
            15
          ],
          [
            10,
            1
          ],
          [
            19,
            18
          ],
          [
            12,
            14
          ],
          [
            18,
            5
          ],
          [
            7,
            13
          ],
          [
            6,
            16
          ],
          [
            13,
            3
          ],
          [
            16,
            7
          ]
        ],
        "optimal_cost": 11007.0,
        "matrix": [
          [
            Infinity,
            708067.0,
            19300.0,
            25818.0,
            26.0,
            436945.0,
            9443.0,
            18901.0,
            1631.0,
            1748.0,
            101190.0,
            4968481.0,
            28751.0,
            85586.0,
            2250557.0,
            7395.0,
            276941.0,
            9325.0,
            15960.0,
            15614.0
          ],
          [
            1057022.0,
            Infinity,
            282129.0,
            7998.0,
            9127.0,
            279878.0,
            15890.0,
            1200.0,
            5453.0,
            63.0,
            1430.0,
            288968.0,
            114228.0,
            69371.0,
            4047.0,
            29364.0,
            5838.0,
            3350331.0,
            1415.0,
            5.0
          ],
          [
            108418.0,
            7450.0,
            Infinity,
            18741.0,
            13.0,
            30450.0,
            20877.0,
            157592.0,
            1213605.0,
            662407.0,
            1116.0,
            3630.0,
            13583.0,
            4699917.0,
            29246.0,
            154709.0,
            24268.0,
            14215.0,
            18390.0,
            2357.0
          ],
          [
            1387.0,
            11508.0,
            29115.0,
            Infinity,
            1292.0,
            4393.0,
            784099.0,
            2992.0,
            100420.0,
            239.0,
            43672.0,
            6353.0,
            6468.0,
            6138.0,
            3851.0,
            2686.0,
            511475.0,
            717.0,
            4575.0,
            8677.0
          ],
          [
            102324.0,
            19076537.0,
            1461.0,
            10760.0,
            Infinity,
            23644.0,
            1060757.0,
            4032.0,
            17951.0,
            15545.0,
            173830.0,
            3931.0,
            24113.0,
            57588.0,
            33.0,
            255447.0,
            28711.0,
            26818.0,
            146693.0,
            20.0
          ],
          [
            54.0,
            435804.0,
            12418.0,
            87125.0,
            4572.0,
            Infinity,
            21629.0,
            55348.0,
            15925.0,
            419.0,
            2111318.0,
            87233.0,
            185576.0,
            112429.0,
            23935.0,
            1601769.0,
            441615.0,
            1213.0,
            669920.0,
            216176.0
          ],
          [
            553604.0,
            8.0,
            57345.0,
            27683.0,
            474.0,
            349126.0,
            Infinity,
            941.0,
            2721.0,
            9063.0,
            246955.0,
            4750.0,
            138895.0,
            20799.0,
            9456.0,
            2299913.0,
            61.0,
            14.0,
            274600.0,
            17108.0
          ],
          [
            13894.0,
            568.0,
            97954.0,
            2053.0,
            1973404.0,
            101077.0,
            174678.0,
            Infinity,
            1232696.0,
            1125.0,
            21169.0,
            1385.0,
            49.0,
            66.0,
            10415.0,
            85129.0,
            511437.0,
            61450.0,
            613728.0,
            5739.0
          ],
          [
            2513.0,
            634549.0,
            6557.0,
            24.0,
            357414.0,
            25943.0,
            23159.0,
            2011.0,
            Infinity,
            1915.0,
            648214.0,
            155.0,
            35162.0,
            37661.0,
            192477.0,
            36576.0,
            650055.0,
            635.0,
            172806.0,
            24671809.0
          ],
          [
            18442.0,
            7427.0,
            68858614.0,
            216.0,
            475916.0,
            122067.0,
            268638.0,
            400.0,
            971988.0,
            Infinity,
            195881.0,
            4572.0,
            1863.0,
            390347.0,
            635.0,
            9432908.0,
            114952.0,
            6315.0,
            4905.0,
            571919.0
          ],
          [
            41934.0,
            9.0,
            5694.0,
            2190.0,
            123.0,
            877143.0,
            2151.0,
            204276.0,
            448444.0,
            510763.0,
            Infinity,
            129399.0,
            119143.0,
            3353.0,
            23505.0,
            328663.0,
            12087.0,
            1694.0,
            812442.0,
            16458.0
          ],
          [
            2837286.0,
            414435.0,
            45265.0,
            5884.0,
            4086.0,
            81899.0,
            463046.0,
            1492.0,
            3248496.0,
            180479.0,
            566521.0,
            Infinity,
            6666.0,
            72211.0,
            608565.0,
            1280.0,
            924335.0,
            63372.0,
            2158.0,
            811.0
          ],
          [
            19158.0,
            4194.0,
            2552525.0,
            47636.0,
            36223.0,
            26872.0,
            13694.0,
            19413.0,
            2278.0,
            47798.0,
            1521.0,
            3490.0,
            Infinity,
            83687.0,
            144.0,
            40981.0,
            75472.0,
            53040.0,
            2649827.0,
            90222.0
          ],
          [
            7257.0,
            691489.0,
            12025084.0,
            939.0,
            735.0,
            156246.0,
            229.0,
            642.0,
            195240.0,
            13530283.0,
            13549.0,
            202510.0,
            949161.0,
            Infinity,
            1884186.0,
            13848.0,
            9336771.0,
            836702.0,
            7892.0,
            1488042.0
          ],
          [
            1855.0,
            5862.0,
            56392.0,
            6571.0,
            1555017.0,
            16369.0,
            185.0,
            12063.0,
            12753.0,
            2599.0,
            205159.0,
            14683.0,
            26960.0,
            5093340.0,
            Infinity,
            18480.0,
            9588298.0,
            617.0,
            44110.0,
            881.0
          ],
          [
            94.0,
            23863.0,
            966666.0,
            45377.0,
            1781.0,
            67510.0,
            101828.0,
            13588.0,
            99.0,
            19.0,
            168.0,
            3322.0,
            2558.0,
            12217.0,
            173825.0,
            Infinity,
            4591.0,
            189374.0,
            6734.0,
            25023969.0
          ],
          [
            11415.0,
            17050.0,
            326842.0,
            1462.0,
            7062.0,
            60120.0,
            4978.0,
            867.0,
            4439.0,
            927109.0,
            113874.0,
            1005876.0,
            10459197.0,
            101286.0,
            3443.0,
            41977310.0,
            Infinity,
            50451.0,
            573493.0,
            122.0
          ],
          [
            15496.0,
            1978.0,
            1051.0,
            62.0,
            308.0,
            2970.0,
            38804.0,
            748995.0,
            2663.0,
            4559.0,
            188732.0,
            547.0,
            268987.0,
            8191.0,
            261.0,
            55950.0,
            94524.0,
            Infinity,
            34492.0,
            649688.0
          ],
          [
            239212.0,
            27296.0,
            35592539.0,
            517.0,
            52746.0,
            1288.0,
            2167.0,
            19249.0,
            2037.0,
            51822.0,
            1212.0,
            2356.0,
            192.0,
            404097.0,
            24585108.0,
            1051.0,
            23601.0,
            22114.0,
            Infinity,
            243.0
          ],
          [
            197108.0,
            370.0,
            397847.0,
            200.0,
            366467.0,
            5373.0,
            34333.0,
            415946.0,
            3758910.0,
            5112.0,
            57950.0,
            2040.0,
            1151.0,
            922910.0,
            31.0,
            354.0,
            109538.0,
            14712.0,
            433.0,
            Infinity
          ]
        ],
        "is_hardest": true
      },
      "iteration_21": {
        "iterations": 131,
        "hardest": 131,
        "optimal_tour": [
          [
            18,
            8
          ],
          [
            6,
            7
          ],
          [
            5,
            2
          ],
          [
            10,
            19
          ],
          [
            1,
            10
          ],
          [
            15,
            13
          ],
          [
            11,
            18
          ],
          [
            0,
            4
          ],
          [
            4,
            12
          ],
          [
            9,
            15
          ],
          [
            2,
            1
          ],
          [
            17,
            9
          ],
          [
            7,
            5
          ],
          [
            14,
            3
          ],
          [
            12,
            11
          ],
          [
            8,
            16
          ],
          [
            13,
            0
          ],
          [
            16,
            14
          ],
          [
            3,
            6
          ],
          [
            19,
            17
          ]
        ],
        "optimal_cost": 10540.0,
        "matrix": [
          [
            Infinity,
            22771.0,
            8854.0,
            17644.0,
            165.0,
            2259.0,
            15398.0,
            7025.0,
            423.0,
            45313.0,
            14305.0,
            28567.0,
            8173.0,
            10067.0,
            1265.0,
            503.0,
            11340.0,
            5217.0,
            5012.0,
            1955637.0
          ],
          [
            4248.0,
            Infinity,
            1729.0,
            5124.0,
            108465.0,
            4451.0,
            4.0,
            20858.0,
            2519652.0,
            14970.0,
            116.0,
            16840737.0,
            43409.0,
            35448177.0,
            1477.0,
            12043941.0,
            40640.0,
            13288.0,
            7947358.0,
            727183.0
          ],
          [
            143951.0,
            442.0,
            Infinity,
            281.0,
            125421.0,
            16635.0,
            1515.0,
            4904.0,
            128761.0,
            317.0,
            74534.0,
            21479.0,
            8619.0,
            40748.0,
            367.0,
            485179.0,
            52558543.0,
            67425.0,
            748.0,
            39155.0
          ],
          [
            1780.0,
            28673.0,
            129795.0,
            Infinity,
            72961.0,
            1385.0,
            181.0,
            7986.0,
            1247.0,
            16359542.0,
            131877302.0,
            2430.0,
            951066.0,
            25896.0,
            340836.0,
            3524.0,
            261893.0,
            39.0,
            48508.0,
            5705.0
          ],
          [
            20357.0,
            4131.0,
            75039.0,
            284.0,
            Infinity,
            34900.0,
            1114.0,
            532.0,
            10871.0,
            348.0,
            27982.0,
            21328.0,
            1735.0,
            8150649.0,
            23600.0,
            76288.0,
            23044.0,
            70046.0,
            642.0,
            228692.0
          ],
          [
            68030.0,
            984.0,
            75.0,
            11800.0,
            653980.0,
            Infinity,
            114846.0,
            7345.0,
            1518.0,
            89776.0,
            462869.0,
            255633.0,
            884787.0,
            970739.0,
            85015.0,
            30484.0,
            4686.0,
            8071.0,
            4734963.0,
            805.0
          ],
          [
            18808.0,
            4208.0,
            128.0,
            4807055.0,
            12604.0,
            11833.0,
            Infinity,
            102.0,
            525.0,
            12313.0,
            877132.0,
            908.0,
            37797.0,
            27615.0,
            41.0,
            1336887.0,
            20611.0,
            85.0,
            1659.0,
            30625.0
          ],
          [
            30930.0,
            75275.0,
            1754206.0,
            13570822.0,
            205069.0,
            177.0,
            13048.0,
            Infinity,
            102.0,
            35769.0,
            3832.0,
            178072.0,
            182706.0,
            158896.0,
            3898.0,
            3918.0,
            809631.0,
            5567569.0,
            85451.0,
            612.0
          ],
          [
            84760.0,
            36010.0,
            17015.0,
            5149.0,
            46636.0,
            11039.0,
            24914.0,
            123881.0,
            Infinity,
            7110.0,
            41103.0,
            4023.0,
            3156.0,
            16518525.0,
            15712.0,
            408554.0,
            520.0,
            45606.0,
            3635.0,
            2741.0
          ],
          [
            406000.0,
            315405.0,
            1010.0,
            16511159.0,
            620507.0,
            166978730.0,
            9269.0,
            74362.0,
            7129.0,
            Infinity,
            480537.0,
            46766.0,
            867.0,
            103157.0,
            1503056.0,
            482.0,
            85291.0,
            86053.0,
            28143.0,
            9518.0
          ],
          [
            90562.0,
            30950.0,
            734.0,
            712.0,
            1241392.0,
            478017.0,
            339284.0,
            1591.0,
            1834.0,
            3577.0,
            Infinity,
            4248.0,
            124662.0,
            2414.0,
            160979.0,
            40018.0,
            13354.0,
            1570304.0,
            43909.0,
            1119.0
          ],
          [
            569170.0,
            18870.0,
            336811.0,
            6593.0,
            663.0,
            12670.0,
            887.0,
            4035355.0,
            105044.0,
            2759231.0,
            150399.0,
            Infinity,
            99952.0,
            16521.0,
            128926.0,
            2091.0,
            1582.0,
            63.0,
            139.0,
            13804.0
          ],
          [
            2758262.0,
            63657.0,
            13790.0,
            164284.0,
            511139.0,
            138176.0,
            8288747.0,
            4262.0,
            175263.0,
            303616.0,
            5125.0,
            3358.0,
            Infinity,
            172726.0,
            344.0,
            35160.0,
            13511.0,
            28129.0,
            94106.0,
            27099.0
          ],
          [
            221.0,
            14337.0,
            10821.0,
            291279.0,
            1317.0,
            524340.0,
            1671.0,
            928.0,
            36428.0,
            25654.0,
            145555.0,
            41831.0,
            16220.0,
            Infinity,
            20855.0,
            4697568.0,
            3284.0,
            1440.0,
            3398117.0,
            70033.0
          ],
          [
            12285.0,
            18132.0,
            610004.0,
            69.0,
            37419.0,
            372136.0,
            3057.0,
            389221.0,
            5041938.0,
            110883.0,
            80621.0,
            11679988.0,
            1875.0,
            2393.0,
            Infinity,
            1523.0,
            834.0,
            67818.0,
            2741.0,
            14410186.0
          ],
          [
            274160.0,
            718.0,
            4288.0,
            157081.0,
            131242.0,
            10423.0,
            3019.0,
            91.0,
            5922.0,
            61536.0,
            211999.0,
            8358.0,
            10648.0,
            216.0,
            41.0,
            Infinity,
            623.0,
            1081.0,
            13299.0,
            2326.0
          ],
          [
            13946.0,
            53453.0,
            2543799.0,
            70374.0,
            78047.0,
            40539.0,
            22673.0,
            87791.0,
            51793.0,
            37780.0,
            42051.0,
            15242.0,
            18888.0,
            11441.0,
            184.0,
            5926.0,
            Infinity,
            20956.0,
            973662.0,
            388920.0
          ],
          [
            36809.0,
            26935.0,
            78776.0,
            35786.0,
            113486.0,
            161904.0,
            14282.0,
            5765355.0,
            366882.0,
            236.0,
            19900.0,
            24143.0,
            95876.0,
            633800.0,
            1701.0,
            1288.0,
            15372.0,
            Infinity,
            1603.0,
            1023024.0
          ],
          [
            21840.0,
            11687.0,
            5832.0,
            5748.0,
            2243.0,
            46958.0,
            62.0,
            119349.0,
            688.0,
            2951.0,
            69318.0,
            6176.0,
            68.0,
            656.0,
            14176.0,
            2045.0,
            2585.0,
            293287.0,
            Infinity,
            2134.0
          ],
          [
            13654.0,
            78144.0,
            21297.0,
            18355.0,
            97255.0,
            2012.0,
            943.0,
            63.0,
            2947.0,
            5884.0,
            623.0,
            97270.0,
            4792.0,
            4981.0,
            4334.0,
            122300.0,
            3837.0,
            315.0,
            3804.0,
            Infinity
          ]
        ],
        "is_hardest": true
      },
      "iteration_30": {
        "iterations": 153,
        "hardest": 153,
        "optimal_tour": [
          [
            10,
            4
          ],
          [
            15,
            10
          ],
          [
            5,
            7
          ],
          [
            3,
            14
          ],
          [
            16,
            0
          ],
          [
            19,
            12
          ],
          [
            14,
            8
          ],
          [
            8,
            15
          ],
          [
            6,
            11
          ],
          [
            4,
            6
          ],
          [
            0,
            2
          ],
          [
            1,
            18
          ],
          [
            7,
            13
          ],
          [
            13,
            17
          ],
          [
            18,
            3
          ],
          [
            12,
            1
          ],
          [
            11,
            16
          ],
          [
            9,
            5
          ],
          [
            2,
            9
          ],
          [
            17,
            19
          ]
        ],
        "optimal_cost": 11417.0,
        "matrix": [
          [
            Infinity,
            409971.0,
            891.0,
            84916.0,
            298.0,
            390269.0,
            32034.0,
            693805.0,
            680.0,
            69598.0,
            70142.0,
            4185.0,
            65265.0,
            1571665.0,
            11516.0,
            246132.0,
            33623.0,
            4366.0,
            1141697.0,
            12659.0
          ],
          [
            52505.0,
            Infinity,
            1700.0,
            560829.0,
            12185.0,
            56965.0,
            219793.0,
            4637.0,
            6019.0,
            173047.0,
            8006.0,
            1186939.0,
            24.0,
            9375.0,
            146532.0,
            4515043.0,
            1649.0,
            81936.0,
            2798.0,
            305302.0
          ],
          [
            1178.0,
            339745.0,
            Infinity,
            25639.0,
            21599.0,
            16034.0,
            21420.0,
            1735565.0,
            1372059.0,
            494.0,
            8053.0,
            1574533.0,
            2212530.0,
            5597.0,
            202.0,
            91815.0,
            255046.0,
            486547.0,
            309804.0,
            563.0
          ],
          [
            255.0,
            1524164.0,
            39800.0,
            Infinity,
            6095.0,
            270743.0,
            4748.0,
            9013.0,
            120029.0,
            6053.0,
            44050.0,
            27837.0,
            21736.0,
            215687.0,
            13.0,
            11710.0,
            6057.0,
            148330.0,
            770839.0,
            44786.0
          ],
          [
            599017.0,
            196990.0,
            1433189.0,
            5759003.0,
            Infinity,
            6318.0,
            82.0,
            78045.0,
            2497974.0,
            37.0,
            143.0,
            19139.0,
            29969.0,
            30188.0,
            7035.0,
            68001.0,
            4987.0,
            1553.0,
            17896.0,
            10997.0
          ],
          [
            924.0,
            12250.0,
            3870.0,
            48920.0,
            37503.0,
            Infinity,
            283799.0,
            161.0,
            9246167.0,
            739650.0,
            742.0,
            76160.0,
            19204.0,
            156496.0,
            14696164.0,
            236435.0,
            10165.0,
            134323.0,
            81794.0,
            333532.0
          ],
          [
            3441.0,
            9127838.0,
            263549.0,
            2144556.0,
            49098.0,
            1568.0,
            Infinity,
            8771320.0,
            548142.0,
            24707.0,
            54608.0,
            993.0,
            54.0,
            1720.0,
            11826.0,
            313.0,
            197084.0,
            10766.0,
            26797.0,
            1268.0
          ],
          [
            56285.0,
            764043.0,
            60986.0,
            5401.0,
            194399.0,
            11052.0,
            446.0,
            Infinity,
            411.0,
            76179.0,
            17839.0,
            8893.0,
            127319790.0,
            898.0,
            33780.0,
            58816.0,
            2944970.0,
            320579.0,
            2213.0,
            15089.0
          ],
          [
            158.0,
            8762.0,
            33419.0,
            244021.0,
            12090.0,
            20862.0,
            155659.0,
            107689.0,
            Infinity,
            11810.0,
            907.0,
            154480.0,
            17331.0,
            17491.0,
            6063.0,
            453.0,
            56923.0,
            120693.0,
            407881.0,
            3391.0
          ],
          [
            6804.0,
            82101.0,
            1176.0,
            1940598.0,
            1269073.0,
            52.0,
            5839.0,
            39206.0,
            1150.0,
            Infinity,
            73299.0,
            1556.0,
            12309.0,
            306523.0,
            1185.0,
            24157.0,
            8579.0,
            104088.0,
            32276.0,
            627.0
          ],
          [
            144399.0,
            17778.0,
            7186.0,
            107531.0,
            84.0,
            118343.0,
            2393.0,
            40615.0,
            181545.0,
            425.0,
            Infinity,
            18.0,
            17859.0,
            156516.0,
            9060.0,
            2210818.0,
            6519.0,
            9887.0,
            31695.0,
            9303.0
          ],
          [
            623598.0,
            1647.0,
            4147.0,
            24851.0,
            4933.0,
            5969.0,
            6260509.0,
            435.0,
            50522613.0,
            7297.0,
            4892001.0,
            Infinity,
            32110.0,
            180.0,
            5779.0,
            157976.0,
            153.0,
            146926.0,
            22949.0,
            22306.0
          ],
          [
            68073.0,
            915.0,
            44549.0,
            214.0,
            41307.0,
            5374.0,
            8044.0,
            222.0,
            5459.0,
            7385.0,
            4294.0,
            115192.0,
            Infinity,
            92480.0,
            13503.0,
            9.0,
            4232.0,
            474.0,
            1946548.0,
            28669.0
          ],
          [
            15882.0,
            989222.0,
            170859.0,
            641797.0,
            415.0,
            426053.0,
            67312.0,
            33110.0,
            21319.0,
            9997.0,
            34727.0,
            5450.0,
            1335.0,
            Infinity,
            14812.0,
            97955.0,
            368703.0,
            144.0,
            376164.0,
            31601.0
          ],
          [
            44746.0,
            43767.0,
            98691.0,
            17443.0,
            50224.0,
            13600.0,
            914853.0,
            774.0,
            156.0,
            1387.0,
            2.0,
            24986.0,
            526.0,
            3713.0,
            Infinity,
            11720.0,
            11778.0,
            38125.0,
            2672193.0,
            2.0
          ],
          [
            507069.0,
            102472.0,
            29897.0,
            110053.0,
            20534.0,
            16003.0,
            16682.0,
            196.0,
            1439.0,
            9861.0,
            88.0,
            9581536.0,
            13350.0,
            2879.0,
            62.0,
            Infinity,
            2103.0,
            9311809.0,
            187044.0,
            3980.0
          ],
          [
            989.0,
            4149.0,
            80136.0,
            19215.0,
            22622.0,
            264628.0,
            36799.0,
            775513.0,
            257522.0,
            1037202.0,
            1437.0,
            79910.0,
            3108.0,
            12139.0,
            44339.0,
            31641.0,
            Infinity,
            21065.0,
            17170.0,
            141990.0
          ],
          [
            935729.0,
            5611.0,
            236800.0,
            66366.0,
            1602.0,
            1124632.0,
            2484799.0,
            70.0,
            2557.0,
            44002.0,
            7844.0,
            98712.0,
            229716.0,
            412158.0,
            63684.0,
            2811.0,
            27269.0,
            Infinity,
            225147.0,
            1478.0
          ],
          [
            303870.0,
            257680.0,
            42072.0,
            107.0,
            27559.0,
            75844.0,
            188349.0,
            21103209.0,
            1044.0,
            3236827.0,
            52.0,
            815.0,
            12321.0,
            1562.0,
            1873.0,
            111128.0,
            8582.0,
            36033.0,
            Infinity,
            13095.0
          ],
          [
            17865.0,
            13270.0,
            2170306.0,
            122826.0,
            3967.0,
            77248.0,
            22342.0,
            5238.0,
            5165.0,
            3268.0,
            183.0,
            38873.0,
            468.0,
            615662.0,
            66228.0,
            12608.0,
            48130.0,
            19549.0,
            29939.0,
            Infinity
          ]
        ],
        "is_hardest": true
      },
      "iteration_54": {
        "iterations": 307,
        "hardest": 307,
        "optimal_tour": [
          [
            13,
            5
          ],
          [
            11,
            1
          ],
          [
            18,
            3
          ],
          [
            4,
            18
          ],
          [
            15,
            12
          ],
          [
            10,
            13
          ],
          [
            8,
            16
          ],
          [
            14,
            10
          ],
          [
            19,
            17
          ],
          [
            1,
            9
          ],
          [
            17,
            6
          ],
          [
            16,
            2
          ],
          [
            12,
            0
          ],
          [
            0,
            4
          ],
          [
            2,
            15
          ],
          [
            5,
            8
          ],
          [
            6,
            14
          ],
          [
            7,
            19
          ],
          [
            3,
            11
          ],
          [
            9,
            7
          ]
        ],
        "optimal_cost": 9850.0,
        "matrix": [
          [
            Infinity,
            4082.0,
            696.0,
            10320.0,
            33.0,
            5362.0,
            64307.0,
            1444666.0,
            36551.0,
            5578234.0,
            1617.0,
            6266.0,
            127614.0,
            276055.0,
            366834.0,
            2782.0,
            11108.0,
            32531.0,
            392583.0,
            109993.0
          ],
          [
            331753.0,
            Infinity,
            29397.0,
            1869238.0,
            1187.0,
            8125.0,
            1.0,
            6189.0,
            9145.0,
            203.0,
            560643.0,
            6140819.0,
            21351.0,
            2157.0,
            116347.0,
            226588.0,
            826478.0,
            15740.0,
            3833937.0,
            6328.0
          ],
          [
            164.0,
            712125.0,
            Infinity,
            6521813.0,
            6501.0,
            158.0,
            9.0,
            10019.0,
            5108038.0,
            49838.0,
            283.0,
            445897.0,
            500482.0,
            148.0,
            6282.0,
            281.0,
            40.0,
            55173.0,
            839.0,
            356075.0
          ],
          [
            35350.0,
            25974.0,
            196135.0,
            Infinity,
            1330.0,
            36.0,
            1107165.0,
            888.0,
            9101242.0,
            2890614.0,
            15262.0,
            573.0,
            91.0,
            59248.0,
            4569634.0,
            1191.0,
            1019.0,
            1478674.0,
            626.0,
            11550.0
          ],
          [
            220.0,
            985.0,
            1361.0,
            720107.0,
            Infinity,
            1419218.0,
            3086.0,
            77.0,
            110230.0,
            12450.0,
            8521.0,
            372877.0,
            48484.0,
            18328.0,
            1311994.0,
            133074.0,
            248948.0,
            16448.0,
            7.0,
            1059.0
          ],
          [
            368.0,
            6062990.0,
            967.0,
            53578.0,
            7253.0,
            Infinity,
            64149.0,
            2747810.0,
            642.0,
            1232598.0,
            39679.0,
            2308920.0,
            55325.0,
            511036.0,
            20979.0,
            70.0,
            1029.0,
            46519.0,
            240779.0,
            3587.0
          ],
          [
            1587450.0,
            904332.0,
            1812.0,
            13158.0,
            1420.0,
            229614.0,
            Infinity,
            1810.0,
            3664.0,
            24482.0,
            33188198.0,
            3069.0,
            5792.0,
            86362.0,
            687.0,
            6235.0,
            21889965.0,
            3178226.0,
            14689.0,
            21103.0
          ],
          [
            7804.0,
            157410.0,
            39990.0,
            431978.0,
            11850312.0,
            3686.0,
            4628.0,
            Infinity,
            117902.0,
            23839.0,
            52203.0,
            4890.0,
            9561.0,
            80808.0,
            7027.0,
            208848.0,
            657717.0,
            370618.0,
            1535027.0,
            373.0
          ],
          [
            3948.0,
            173.0,
            1801.0,
            91171.0,
            717.0,
            1213438.0,
            32211.0,
            769083.0,
            Infinity,
            857986.0,
            41292.0,
            133932.0,
            3664415.0,
            259.0,
            230851.0,
            7901.0,
            667.0,
            1022.0,
            179224.0,
            264.0
          ],
          [
            55340.0,
            7841.0,
            201322.0,
            60538.0,
            628.0,
            3058.0,
            182948.0,
            1091.0,
            27117.0,
            Infinity,
            29683.0,
            1263.0,
            129514.0,
            3853.0,
            6226.0,
            215682.0,
            3121.0,
            1818.0,
            8561.0,
            57523.0
          ],
          [
            664763.0,
            13211.0,
            2207.0,
            121.0,
            36.0,
            8163.0,
            168805296.0,
            1402.0,
            1940.0,
            813331.0,
            Infinity,
            3335148.0,
            62066.0,
            467.0,
            19157.0,
            4449.0,
            530918.0,
            338141.0,
            586.0,
            815.0
          ],
          [
            53.0,
            987.0,
            1254.0,
            54746.0,
            72274.0,
            3.0,
            3442.0,
            50596.0,
            206806.0,
            504.0,
            50675.0,
            Infinity,
            25988.0,
            84846.0,
            44504.0,
            16082.0,
            9505.0,
            173041.0,
            656206.0,
            1404.0
          ],
          [
            685.0,
            3344.0,
            3294.0,
            0.0,
            261600.0,
            208589.0,
            1937050.0,
            17152.0,
            149200.0,
            1230.0,
            3151.0,
            2931.0,
            Infinity,
            89590.0,
            1150.0,
            23342.0,
            61164.0,
            201529.0,
            367625.0,
            20338.0
          ],
          [
            2280.0,
            71777.0,
            39066.0,
            1349.0,
            2554257.0,
            930.0,
            35606.0,
            318502.0,
            153858.0,
            5517.0,
            4091.0,
            22856.0,
            3476.0,
            Infinity,
            31004.0,
            11914.0,
            47960.0,
            642425.0,
            24822.0,
            162676.0
          ],
          [
            1877.0,
            2029308.0,
            46865.0,
            25.0,
            1567.0,
            6299.0,
            165.0,
            25730.0,
            3094.0,
            7434.0,
            299.0,
            21161412.0,
            5615.0,
            23607.0,
            Infinity,
            24632.0,
            42058.0,
            378337.0,
            453711.0,
            679030.0
          ],
          [
            3601.0,
            2816.0,
            6883.0,
            43.0,
            900.0,
            3209.0,
            222443.0,
            13108.0,
            27790.0,
            26144.0,
            17181.0,
            7019.0,
            591.0,
            29617.0,
            15292.0,
            Infinity,
            14141.0,
            163080.0,
            13591.0,
            1127330.0
          ],
          [
            666102.0,
            4258.0,
            79.0,
            424088.0,
            21.0,
            17483639.0,
            38094412.0,
            10673.0,
            7574.0,
            9379.0,
            954.0,
            10154.0,
            2784.0,
            1649.0,
            23816.0,
            154733.0,
            Infinity,
            5876.0,
            882.0,
            409.0
          ],
          [
            465078.0,
            2771.0,
            279.0,
            20114.0,
            1498.0,
            6723.0,
            145.0,
            35114.0,
            18515.0,
            750246.0,
            471993.0,
            10821.0,
            883151.0,
            19929.0,
            5825.0,
            275819.0,
            20417142.0,
            Infinity,
            10257.0,
            32868.0
          ],
          [
            889916.0,
            483470.0,
            107421.0,
            690.0,
            110677.0,
            216.0,
            59512.0,
            3224452.0,
            81840.0,
            9352.0,
            31615.0,
            838722.0,
            38844.0,
            4707.0,
            2550.0,
            15405.0,
            111898.0,
            13999.0,
            Infinity,
            43552.0
          ],
          [
            371827.0,
            22536.0,
            10.0,
            17464.0,
            1546.0,
            589613.0,
            55801.0,
            640483.0,
            26607668.0,
            2678.0,
            465.0,
            602.0,
            434312.0,
            271893.0,
            302705.0,
            390939.0,
            203963.0,
            420.0,
            346853.0,
            Infinity
          ]
        ],
        "is_hardest": true
      },
      "iteration_67": {
        "iterations": 477,
        "hardest": 477,
        "optimal_tour": [
          [
            13,
            19
          ],
          [
            9,
            15
          ],
          [
            7,
            11
          ],
          [
            4,
            17
          ],
          [
            5,
            6
          ],
          [
            19,
            16
          ],
          [
            10,
            3
          ],
          [
            8,
            5
          ],
          [
            16,
            0
          ],
          [
            12,
            18
          ],
          [
            14,
            2
          ],
          [
            18,
            7
          ],
          [
            0,
            10
          ],
          [
            1,
            12
          ],
          [
            3,
            4
          ],
          [
            11,
            13
          ],
          [
            6,
            1
          ],
          [
            2,
            8
          ],
          [
            15,
            14
          ],
          [
            17,
            9
          ]
        ],
        "optimal_cost": 10333.0,
        "matrix": [
          [
            Infinity,
            237067.0,
            5726.0,
            654.0,
            1545.0,
            1417.0,
            3758.0,
            979.0,
            122108.0,
            3039454.0,
            175.0,
            4108550.0,
            3397.0,
            6363.0,
            1476580.0,
            6001.0,
            5870.0,
            114156.0,
            78.0,
            552.0
          ],
          [
            7360.0,
            Infinity,
            167026.0,
            26834.0,
            170803.0,
            117012.0,
            745.0,
            737385.0,
            55469.0,
            129606.0,
            1259062.0,
            1520622.0,
            452.0,
            6222179.0,
            38492.0,
            700.0,
            108954.0,
            23438.0,
            4237.0,
            1571.0
          ],
          [
            568.0,
            6264910.0,
            Infinity,
            401532.0,
            26160.0,
            2807190.0,
            279999.0,
            637.0,
            756.0,
            722.0,
            4711970.0,
            143654.0,
            38832.0,
            462752.0,
            13593.0,
            1897.0,
            2761.0,
            298414.0,
            386571.0,
            98271.0
          ],
          [
            345244.0,
            23493.0,
            6265.0,
            Infinity,
            111.0,
            163683.0,
            82075.0,
            7208.0,
            6062.0,
            25714.0,
            85298.0,
            361.0,
            45.0,
            32571.0,
            3631.0,
            12650.0,
            32815.0,
            208486.0,
            1112.0,
            1561669.0
          ],
          [
            88514.0,
            4245105.0,
            250.0,
            37.0,
            Infinity,
            25637.0,
            59917.0,
            8499.0,
            1151656.0,
            2080.0,
            19833.0,
            3515.0,
            4314.0,
            51592.0,
            2998795.0,
            1049382.0,
            192.0,
            1342.0,
            27939.0,
            27753.0
          ],
          [
            3200.0,
            104351.0,
            143.0,
            794929.0,
            7106.0,
            Infinity,
            1828.0,
            343569.0,
            100658.0,
            1961.0,
            395596.0,
            20597.0,
            2292.0,
            682628.0,
            385428.0,
            95528.0,
            481654.0,
            4193.0,
            45114.0,
            3351.0
          ],
          [
            473605.0,
            58.0,
            5078.0,
            54332.0,
            32762.0,
            122880.0,
            Infinity,
            14437.0,
            4764.0,
            492065.0,
            15592.0,
            910.0,
            306043.0,
            205.0,
            22825.0,
            2551.0,
            2664.0,
            7203.0,
            4308.0,
            549140.0
          ],
          [
            875581.0,
            57329.0,
            15117.0,
            3.0,
            13068263.0,
            50330.0,
            3022.0,
            Infinity,
            5577.0,
            1526.0,
            78654.0,
            30.0,
            8031.0,
            232861.0,
            13334.0,
            1315824.0,
            573115.0,
            5072.0,
            4375.0,
            633199.0
          ],
          [
            561187.0,
            1750439.0,
            449678.0,
            191435.0,
            8709.0,
            691.0,
            1102.0,
            535261.0,
            Infinity,
            23666.0,
            1524.0,
            276837.0,
            55609.0,
            30270.0,
            884403.0,
            17939.0,
            56.0,
            1299046.0,
            275996.0,
            358481.0
          ],
          [
            36181.0,
            559997.0,
            1829.0,
            5697.0,
            145246.0,
            57695.0,
            6460.0,
            19707.0,
            43150.0,
            Infinity,
            9549.0,
            662.0,
            2613052.0,
            21203635.0,
            85998.0,
            210.0,
            328482.0,
            549.0,
            440268.0,
            40831.0
          ],
          [
            8115.0,
            119767.0,
            113664.0,
            150.0,
            24489.0,
            1888.0,
            28796916.0,
            35633.0,
            202229.0,
            65117.0,
            Infinity,
            27263.0,
            5077.0,
            3646.0,
            15055.0,
            485161.0,
            7.0,
            25604464.0,
            27421.0,
            2308607.0
          ],
          [
            39022.0,
            2587.0,
            1349.0,
            4435.0,
            686422.0,
            123.0,
            297559.0,
            10213.0,
            237446.0,
            437.0,
            91816.0,
            Infinity,
            1773.0,
            6.0,
            11481.0,
            117035.0,
            28948.0,
            23316.0,
            1665.0,
            857.0
          ],
          [
            410.0,
            13069.0,
            42172.0,
            135.0,
            51018.0,
            423.0,
            35678.0,
            103667.0,
            30520.0,
            134295.0,
            2049.0,
            3596431.0,
            Infinity,
            16371.0,
            654.0,
            20726.0,
            201066.0,
            49150.0,
            80.0,
            1059.0
          ],
          [
            157539.0,
            4625.0,
            9662.0,
            12998482.0,
            232938.0,
            73070.0,
            9169507.0,
            6907.0,
            247753.0,
            25280.0,
            413024.0,
            149.0,
            1562.0,
            Infinity,
            307.0,
            138.0,
            89972.0,
            89029.0,
            789.0,
            1744.0
          ],
          [
            4597.0,
            1364847.0,
            59.0,
            54532.0,
            2870.0,
            5009696.0,
            2505.0,
            564555.0,
            623166.0,
            794.0,
            4948.0,
            18499.0,
            18774.0,
            57915.0,
            Infinity,
            1992.0,
            38592.0,
            62092.0,
            3849.0,
            18788.0
          ],
          [
            1328961.0,
            16924.0,
            82.0,
            222.0,
            12608.0,
            11597.0,
            13165.0,
            1150775.0,
            4118.0,
            4975545.0,
            1398.0,
            32141.0,
            92816.0,
            102630.0,
            646.0,
            Infinity,
            2188167.0,
            59806.0,
            484201.0,
            1867.0
          ],
          [
            46.0,
            95919.0,
            180877.0,
            16300.0,
            281877.0,
            67418.0,
            120812.0,
            2530.0,
            759466.0,
            269814.0,
            14800.0,
            33624.0,
            8085.0,
            16946.0,
            791687.0,
            131.0,
            Infinity,
            541400.0,
            8305.0,
            103.0
          ],
          [
            2886.0,
            47064950.0,
            103375.0,
            134831.0,
            22510.0,
            639999.0,
            246746.0,
            93038.0,
            161779.0,
            40.0,
            292343.0,
            257732.0,
            7171.0,
            89301.0,
            46.0,
            4217.0,
            71814.0,
            Infinity,
            1266.0,
            6693.0
          ],
          [
            43097.0,
            279625.0,
            627212.0,
            151412.0,
            87118.0,
            13278.0,
            463929.0,
            1903.0,
            45343.0,
            299787.0,
            456772.0,
            2299.0,
            56310.0,
            67714.0,
            7059.0,
            61697.0,
            463.0,
            1036724.0,
            Infinity,
            2321937.0
          ],
          [
            19230.0,
            469441.0,
            163630.0,
            84910.0,
            2359.0,
            16044.0,
            350.0,
            28863.0,
            3667.0,
            213060.0,
            17436.0,
            18805.0,
            7297.0,
            4101651.0,
            4438167.0,
            245102.0,
            6.0,
            1507.0,
            29645.0,
            Infinity
          ]
        ],
        "is_hardest": true
      }
    },
    "local_optima": {
      "-4433943819473046178": {
        "iterations": 60,
        "cost": 6374.0,
        "is_hardest": true
      },
      "-36129509944167588": {
        "iterations": 18,
        "cost": 8278.0,
        "is_hardest": false
      },
      "-3814140442137818208": {
        "iterations": 93,
        "cost": 8627.0,
        "is_hardest": true
      },
      "8738296534102456760": {
        "iterations": 18,
        "cost": 10999.0,
        "is_hardest": false
      },
      "569858986772104920": {
        "iterations": 57,
        "cost": 10604.0,
        "is_hardest": false
      },
      "-4816649934195053554": {
        "iterations": 70,
        "cost": 11208.0,
        "is_hardest": false
      },
      "-2586097658970898556": {
        "iterations": 50,
        "cost": 6005.0,
        "is_hardest": false
      },
      "-3890290115790222423": {
        "iterations": 21,
        "cost": 6256.0,
        "is_hardest": false
      },
      "-5481881929537888941": {
        "iterations": 43,
        "cost": 20735.0,
        "is_hardest": false
      },
      "5009899413768398486": {
        "iterations": 57,
        "cost": 15865.0,
        "is_hardest": false
      },
      "-847382130839316180": {
        "iterations": 79,
        "cost": 9386.0,
        "is_hardest": false
      },
      "4512911822656610169": {
        "iterations": 59,
        "cost": 8913.0,
        "is_hardest": false
      },
      "-5174734602219063950": {
        "iterations": 94,
        "cost": 8990.0,
        "is_hardest": true
      },
      "5635240409013136505": {
        "iterations": 43,
        "cost": 8843.0,
        "is_hardest": false
      },
      "-7182808661869265474": {
        "iterations": 33,
        "cost": 8232.0,
        "is_hardest": false
      },
      "4634794284919449625": {
        "iterations": 43,
        "cost": 7483.0,
        "is_hardest": false
      },
      "2031109784245149718": {
        "iterations": 45,
        "cost": 12022.0,
        "is_hardest": false
      },
      "1013555467860468719": {
        "iterations": 27,
        "cost": 14725.0,
        "is_hardest": false
      },
      "-7807658718236993259": {
        "iterations": 129,
        "cost": 11007.0,
        "is_hardest": true
      },
      "-5144007710025579980": {
        "iterations": 35,
        "cost": 8447.0,
        "is_hardest": false
      },
      "3277374824787957599": {
        "iterations": 51,
        "cost": 7111.0,
        "is_hardest": false
      },
      "-2870860393559433247": {
        "iterations": 131,
        "cost": 10540.0,
        "is_hardest": true
      },
      "-7808997414157806451": {
        "iterations": 37,
        "cost": 7838.0,
        "is_hardest": false
      },
      "2038774197098308283": {
        "iterations": 36,
        "cost": 9640.0,
        "is_hardest": false
      },
      "6735524723182472730": {
        "iterations": 95,
        "cost": 8108.0,
        "is_hardest": false
      },
      "-5106785378531758252": {
        "iterations": 54,
        "cost": 22405.0,
        "is_hardest": false
      },
      "1929248851239069485": {
        "iterations": 59,
        "cost": 8134.0,
        "is_hardest": false
      },
      "-5729749321251961181": {
        "iterations": 28,
        "cost": 7962.0,
        "is_hardest": false
      },
      "4043196358692563269": {
        "iterations": 45,
        "cost": 6964.0,
        "is_hardest": false
      },
      "-4455868555129573353": {
        "iterations": 58,
        "cost": 8729.0,
        "is_hardest": false
      },
      "-3286150483142270320": {
        "iterations": 153,
        "cost": 11417.0,
        "is_hardest": true
      },
      "1186033321439814110": {
        "iterations": 128,
        "cost": 11308.0,
        "is_hardest": false
      },
      "2355028678913997062": {
        "iterations": 84,
        "cost": 17351.0,
        "is_hardest": false
      },
      "1326398252430733768": {
        "iterations": 26,
        "cost": 7531.0,
        "is_hardest": false
      },
      "3525499562215536145": {
        "iterations": 47,
        "cost": 10950.0,
        "is_hardest": false
      },
      "4534402415336848018": {
        "iterations": 57,
        "cost": 7770.0,
        "is_hardest": false
      },
      "646960693907279245": {
        "iterations": 51,
        "cost": 11456.0,
        "is_hardest": false
      },
      "-8355179918008376312": {
        "iterations": 116,
        "cost": 18794.0,
        "is_hardest": false
      },
      "-2244340583851418908": {
        "iterations": 45,
        "cost": 9412.0,
        "is_hardest": false
      },
      "5075098704857262306": {
        "iterations": 48,
        "cost": 11611.0,
        "is_hardest": false
      },
      "496969165636220464": {
        "iterations": 109,
        "cost": 6167.0,
        "is_hardest": false
      },
      "1431341806439658261": {
        "iterations": 30,
        "cost": 10170.0,
        "is_hardest": false
      },
      "-7001169054231079600": {
        "iterations": 130,
        "cost": 14400.0,
        "is_hardest": false
      },
      "4084618602807728674": {
        "iterations": 92,
        "cost": 14157.0,
        "is_hardest": false
      },
      "7975901668019791196": {
        "iterations": 41,
        "cost": 5956.0,
        "is_hardest": false
      },
      "-5406084188841157771": {
        "iterations": 92,
        "cost": 9300.0,
        "is_hardest": false
      },
      "4637043229764779326": {
        "iterations": 114,
        "cost": 13068.0,
        "is_hardest": false
      },
      "-4322480363464626020": {
        "iterations": 72,
        "cost": 7173.0,
        "is_hardest": false
      },
      "97012954177844197": {
        "iterations": 21,
        "cost": 6808.0,
        "is_hardest": false
      },
      "7551208832087950914": {
        "iterations": 105,
        "cost": 9744.0,
        "is_hardest": false
      },
      "-2722268425388494203": {
        "iterations": 87,
        "cost": 9833.0,
        "is_hardest": false
      },
      "3007288017336771546": {
        "iterations": 60,
        "cost": 10647.0,
        "is_hardest": false
      },
      "2550420349228540818": {
        "iterations": 83,
        "cost": 5591.0,
        "is_hardest": false
      },
      "7475912139283552580": {
        "iterations": 20,
        "cost": 8854.0,
        "is_hardest": false
      },
      "-1069237965168408792": {
        "iterations": 307,
        "cost": 9850.0,
        "is_hardest": true
      },
      "6933897116946087174": {
        "iterations": 101,
        "cost": 5751.0,
        "is_hardest": false
      },
      "-2721320756894024662": {
        "iterations": 133,
        "cost": 10415.0,
        "is_hardest": false
      },
      "-285202785000350311": {
        "iterations": 280,
        "cost": 10910.0,
        "is_hardest": false
      },
      "-7887353083263911051": {
        "iterations": 36,
        "cost": 12004.0,
        "is_hardest": false
      },
      "-6912160031357336533": {
        "iterations": 55,
        "cost": 13321.0,
        "is_hardest": false
      },
      "7191403740591817326": {
        "iterations": 94,
        "cost": 9768.0,
        "is_hardest": false
      },
      "-634103561096318793": {
        "iterations": 67,
        "cost": 6347.0,
        "is_hardest": false
      },
      "5412134225668902767": {
        "iterations": 68,
        "cost": 10134.0,
        "is_hardest": false
      },
      "6191664108379458355": {
        "iterations": 52,
        "cost": 7021.0,
        "is_hardest": false
      },
      "-4894527452879590942": {
        "iterations": 60,
        "cost": 7029.0,
        "is_hardest": false
      },
      "-2552260812423782074": {
        "iterations": 119,
        "cost": 8096.0,
        "is_hardest": false
      },
      "2337633870065871007": {
        "iterations": 82,
        "cost": 8461.0,
        "is_hardest": false
      },
      "680483623941053809": {
        "iterations": 477,
        "cost": 10333.0,
        "is_hardest": true
      },
      "-5871512568702669519": {
        "iterations": 43,
        "cost": 17334.0,
        "is_hardest": false
      },
      "4488695038341816511": {
        "iterations": 41,
        "cost": 10812.0,
        "is_hardest": false
      },
      "-3616474965350131806": {
        "iterations": 118,
        "cost": 21253.0,
        "is_hardest": false
      },
      "3423105723246545871": {
        "iterations": 61,
        "cost": 15680.0,
        "is_hardest": false
      },
      "-6093281438010321188": {
        "iterations": 24,
        "cost": 11580.0,
        "is_hardest": false
      },
      "1180973087578413051": {
        "iterations": 44,
        "cost": 8620.0,
        "is_hardest": false
      },
      "4158403649280957420": {
        "iterations": 89,
        "cost": 10059.0,
        "is_hardest": false
      },
      "-4819044971536174167": {
        "iterations": 45,
        "cost": 6224.0,
        "is_hardest": false
      },
      "6532763528106829537": {
        "iterations": 33,
        "cost": 17795.0,
        "is_hardest": false
      },
      "-7535913808786586812": {
        "iterations": 156,
        "cost": 8666.0,
        "is_hardest": false
      },
      "466649588206863754": {
        "iterations": 19,
        "cost": 11981.0,
        "is_hardest": false
      },
      "2931981957804931598": {
        "iterations": 35,
        "cost": 9572.0,
        "is_hardest": false
      },
      "3666908751458794780": {
        "iterations": 107,
        "cost": 9188.0,
        "is_hardest": false
      },
      "-4581003076352298542": {
        "iterations": 117,
        "cost": 14037.0,
        "is_hardest": false
      },
      "-2896832478674076517": {
        "iterations": 36,
        "cost": 5373.0,
        "is_hardest": false
      },
      "8897682974877131181": {
        "iterations": 28,
        "cost": 9007.0,
        "is_hardest": false
      },
      "-4697972465531766453": {
        "iterations": 38,
        "cost": 8797.0,
        "is_hardest": false
      },
      "-5550397527848716801": {
        "iterations": 87,
        "cost": 10182.0,
        "is_hardest": false
      },
      "1022454719535661485": {
        "iterations": 58,
        "cost": 5219.0,
        "is_hardest": false
      },
      "-1025830802802823923": {
        "iterations": 119,
        "cost": 7200.0,
        "is_hardest": false
      },
      "2212000210773758970": {
        "iterations": 135,
        "cost": 12652.0,
        "is_hardest": false
      },
      "-5749835717390637360": {
        "iterations": 86,
        "cost": 8376.0,
        "is_hardest": false
      },
      "8706955408478085309": {
        "iterations": 38,
        "cost": 5718.0,
        "is_hardest": false
      },
      "-4008492367665588678": {
        "iterations": 91,
        "cost": 17150.0,
        "is_hardest": false
      },
      "-2043436963305839693": {
        "iterations": 60,
        "cost": 14528.0,
        "is_hardest": false
      },
      "5464283534995079548": {
        "iterations": 68,
        "cost": 9670.0,
        "is_hardest": false
      },
      "-8230949694045703047": {
        "iterations": 73,
        "cost": 10393.0,
        "is_hardest": false
      },
      "6034976471023176501": {
        "iterations": 63,
        "cost": 8217.0,
        "is_hardest": false
      },
      "-5567714766687097244": {
        "iterations": 121,
        "cost": 6723.0,
        "is_hardest": false
      },
      "-8458186965698998169": {
        "iterations": 33,
        "cost": 9031.0,
        "is_hardest": false
      },
      "3036318662677531106": {
        "iterations": 30,
        "cost": 4339.0,
        "is_hardest": false
      },
      "5825101570625965892": {
        "iterations": 18,
        "cost": 9244.0,
        "is_hardest": false
      }
    },
    "transitions": {},
    "last_matrix": [],
    "all_iterations": [
      60,
      18,
      93,
      18,
      57,
      70,
      50,
      21,
      43,
      57,
      79,
      59,
      94,
      43,
      33,
      43,
      45,
      27,
      129,
      35,
      51,
      131,
      37,
      36,
      95,
      54,
      59,
      28,
      45,
      58,
      153,
      128,
      84,
      26,
      47,
      57,
      51,
      116,
      45,
      48,
      109,
      30,
      130,
      92,
      41,
      92,
      114,
      72,
      21,
      105,
      87,
      60,
      83,
      20,
      307,
      101,
      133,
      280,
      36,
      55,
      94,
      67,
      68,
      52,
      60,
      119,
      82,
      477,
      43,
      41,
      118,
      61,
      24,
      44,
      89,
      45,
      33,
      156,
      19,
      35,
      107,
      117,
      36,
      28,
      38,
      87,
      58,
      119,
      135,
      86,
      38,
      91,
      60,
      68,
      73,
      63,
      121,
      33,
      30,
      18
    ]
  }
}